diagnostic_and_simulation_base/README.md
diagnostic_and_simulation_base/__init__.py
diagnostic_and_simulation_base/diagnostic_and_simulation_base.py
diagnostic_and_simulation_base/nested_dictionary.py
diagnostic_and_simulation_base/py.typed
diagnostic_and_simulation_base/utility/get_python_library.py
diagnostic_and_simulation_base/utility/get_version.py
diagnostic_and_simulation_base/utility/logging.py
diagnostic_and_simulation_base/utility/make_settings_json.py
diagnostic_and_simulation_base/version_storage.py
gsfit-0.0.3.dist-info/METADATA
gsfit-0.0.3.dist-info/WHEEL
gsfit-0.0.3.dist-info/licenses/LICENSE
gsfit/__init__.py
gsfit/database_readers/__init__.py
gsfit/database_readers/freegs/__init__.py
gsfit/database_readers/freegs/setup_bp_probes.py
gsfit/database_readers/freegs/setup_coils.py
gsfit/database_readers/freegs/setup_dialoop.py
gsfit/database_readers/freegs/setup_flux_loops.py
gsfit/database_readers/freegs/setup_isoflux_boundary_sensors.py
gsfit/database_readers/freegs/setup_isoflux_sensors.py
gsfit/database_readers/freegs/setup_passives.py
gsfit/database_readers/freegs/setup_plasma.py
gsfit/database_readers/freegs/setup_pressure_sensors.py
gsfit/database_readers/freegs/setup_rogowski_coils.py
gsfit/database_readers/freegsnke/__init__.py
gsfit/database_readers/freegsnke/setup_bp_probes.py
gsfit/database_readers/freegsnke/setup_coils.py
gsfit/database_readers/freegsnke/setup_dialoop.py
gsfit/database_readers/freegsnke/setup_flux_loops.py
gsfit/database_readers/freegsnke/setup_isoflux_boundary_sensors.py
gsfit/database_readers/freegsnke/setup_isoflux_sensors.py
gsfit/database_readers/freegsnke/setup_passives.py
gsfit/database_readers/freegsnke/setup_plasma.py
gsfit/database_readers/freegsnke/setup_pressure_sensors.py
gsfit/database_readers/freegsnke/setup_rogowski_coils.py
gsfit/database_readers/interface.py
gsfit/database_readers/st40_astra_mdsplus/__init__.py
gsfit/database_readers/st40_astra_mdsplus/setup_bp_probes.py
gsfit/database_readers/st40_astra_mdsplus/setup_coils.py
gsfit/database_readers/st40_astra_mdsplus/setup_coils_CORRECT.py
gsfit-0.0.3.dist-info/RECORD
