Metadata-Version: 2.4
Name: gsfit
Version: 0.0.3
Classifier: Programming Language :: Rust
Classifier: Programming Language :: Python :: Implementation :: CPython
Classifier: Programming Language :: Python :: Implementation :: PyPy
Requires-Dist: f90nml
Requires-Dist: matplotlib
Requires-Dist: numpy
Requires-Dist: scipy
Requires-Dist: setuptools-git-versioning
Requires-Dist: toml
Requires-Dist: ipykernel ; extra == 'dev'
Requires-Dist: ipympl ; extra == 'dev'
Requires-Dist: maturin[patchelf] ; platform_system != 'Windows' and extra == 'dev'
Requires-Dist: maturin ; platform_system == 'Windows' and extra == 'dev'
Requires-Dist: mypy ; extra == 'dev'
Requires-Dist: nbval ; extra == 'dev'
Requires-Dist: pytest ; extra == 'dev'
Requires-Dist: pytest-cov ; extra == 'dev'
Requires-Dist: pytest-mypy ; extra == 'dev'
Requires-Dist: pytest-xdist ; extra == 'dev'
Requires-Dist: scipy-stubs ; extra == 'dev'
Requires-Dist: shapely ; extra == 'dev'
Requires-Dist: types-shapely ; extra == 'dev'
Requires-Dist: st40-database ; extra == 'with-st40-mdsplus'
Requires-Dist: standard-utility ; extra == 'with-st40-mdsplus'
Requires-Dist: freegs ; extra == 'with-freegs-and-freegsnke'
Requires-Dist: freegsnke ; extra == 'with-freegs-and-freegsnke'
Requires-Dist: freegs4e ; extra == 'with-freegs-and-freegsnke'
Provides-Extra: dev
Provides-Extra: with_st40_mdsplus
Provides-Extra: with_freegs_and_freegsnke
License-File: LICENSE
Summary: GSFit: Equilibrium reconstruction
Author-email: Peter Buxton <peter.buxton@tokamakenergy.com>
Requires-Python: >=3.11
